README.md
setup.cfg
setup.py
cloudmersive_convert_api_client/__init__.py
cloudmersive_convert_api_client/api_client.py
cloudmersive_convert_api_client/configuration.py
cloudmersive_convert_api_client/rest.py
cloudmersive_convert_api_client.egg-info/PKG-INFO
cloudmersive_convert_api_client.egg-info/SOURCES.txt
cloudmersive_convert_api_client.egg-info/dependency_links.txt
cloudmersive_convert_api_client.egg-info/requires.txt
cloudmersive_convert_api_client.egg-info/top_level.txt
cloudmersive_convert_api_client/api/__init__.py
cloudmersive_convert_api_client/api/compare_document_api.py
cloudmersive_convert_api_client/api/convert_data_api.py
cloudmersive_convert_api_client/api/convert_document_api.py
cloudmersive_convert_api_client/api/convert_image_api.py
cloudmersive_convert_api_client/api/convert_template_api.py
cloudmersive_convert_api_client/api/convert_web_api.py
cloudmersive_convert_api_client/api/edit_document_api.py
cloudmersive_convert_api_client/api/edit_html_api.py
cloudmersive_convert_api_client/api/edit_pdf_api.py
cloudmersive_convert_api_client/api/edit_text_api.py
cloudmersive_convert_api_client/api/merge_document_api.py
cloudmersive_convert_api_client/api/split_document_api.py
cloudmersive_convert_api_client/api/transform_document_api.py
cloudmersive_convert_api_client/api/validate_document_api.py
cloudmersive_convert_api_client/api/viewer_tools_api.py
cloudmersive_convert_api_client/api/zip_archive_api.py
cloudmersive_convert_api_client/models/__init__.py
cloudmersive_convert_api_client/models/add_pdf_annotation_request.py
cloudmersive_convert_api_client/models/alternate_file_format_candidate.py
cloudmersive_convert_api_client/models/append_xlsx_row_request.py
cloudmersive_convert_api_client/models/append_xlsx_row_response.py
cloudmersive_convert_api_client/models/autodetect_document_validation_result.py
cloudmersive_convert_api_client/models/autodetect_get_info_result.py
cloudmersive_convert_api_client/models/autodetect_to_jpg_result.py
cloudmersive_convert_api_client/models/autodetect_to_png_result.py
cloudmersive_convert_api_client/models/autodetect_to_thumbnails_result.py
cloudmersive_convert_api_client/models/base64_decode_request.py
cloudmersive_convert_api_client/models/base64_decode_response.py
