Metadata-Version: 2.1
Name: cloudmersive-convert-api-client
Version: 3.3.0
Summary: convertapi
Home-page: https://www.cloudmersive.com/convert-api
Author-email: 
License: UNKNOWN
Keywords: Swagger,convertapi
Platform: UNKNOWN
